pattern_pack/__init__.py
pattern_pack/pattern1.py
susmita_pattern_printing-0.1.1.dist-info/licenses/license
susmita_pattern_printing-0.1.1.dist-info/METADATA
susmita_pattern_printing-0.1.1.dist-info/WHEEL
susmita_pattern_printing-0.1.1.dist-info/top_level.txt
susmita_pattern_printing-0.1.1.dist-info/RECORD
